[{"videoWebUrl": "https://www.tiktok.com/@themajorkeyes/video/7605052395382377742", "submittedVideoUrl": "https://www.tiktok.com/@themajorkeyes/video/7605052395382377742", "input": "https://www.tiktok.com/@themajorkeyes/video/7605052395382377742", "cid": "7607892292183311117", "createTime": 1771350484, "createTimeISO": "2026-02-17T17:48:04.000Z", "text": "what’s the point in taking their phones and then letting them go on a tv ..?🥀", "diggCount": 89, "likedByAuthor": false, "pinnedByAuthor": false, "repliesToId": null, "replyCommentTotal": 13, "uid": "7563559242305668109", "uniqueId": "unknown.nahla_x", "avatarThumbnail": "https://p19-common-sign.tiktokcdn-us.com/tos-useast5-avt-0068-tx/4e2b72402c925a485f2909010c4b85c3~tplv-tiktokx-cropcenter:100:100.jpg?dr=9640&refresh_token=8dbef361&x-expires=1775750400&x-signature=QWagEoZ6Dr%2FxXGg6RQ8RoKFlIrw%3D&t=4d5b0474&ps=13740610&shp=30310797&shcp=ff37627b&idc=useast8", "mentions": [], "detailedMentions": [], "text_zh": "拿走他们的手机，然后让他们在电视上玩...这有什么意义呢？🥀"}, {"videoWebUrl": "https://www.tiktok.com/@themajorkeyes/video/7605052395382377742", "submittedVideoUrl": "https://www.tiktok.com/@themajorkeyes/video/7605052395382377742", "input": "https://www.tiktok.com/@themajorkeyes/video/7605052395382377742", "cid": "7608079403252171533", "createTime": 1771394087, "createTimeISO": "2026-02-18T05:54:47.000Z", "text": "A TV is also a screen so it’s basically a Screen Time too", "diggCount": 2, "likedByAuthor": false, "pinnedByAuthor": false, "repliesToId": null, "replyCommentTotal": 4, "uid": "7384157726505960490", "uniqueId": "frutigeraero167", "avatarThumbnail": "https://p16-common-sign.tiktokcdn-us.com/tos-useast5-avt-0068-tx/ec75d447f85bff57860814f225f816d1~tplv-tiktokx-cropcenter:100:100.jpg?dr=9640&refresh_token=a688cf15&x-expires=1775750400&x-signature=RjGJHu1qidmOF2BvMVHtYQkufoA%3D&t=4d5b0474&ps=13740610&shp=30310797&shcp=ff37627b&idc=useast8", "mentions": [], "detailedMentions": [], "text_zh": "电视也是屏幕，所以它本质上也是屏幕时间"}, {"videoWebUrl": "https://www.tiktok.com/@themajorkeyes/video/7605052395382377742", "submittedVideoUrl": "https://www.tiktok.com/@themajorkeyes/video/7605052395382377742", "input": "https://www.tiktok.com/@themajorkeyes/video/7605052395382377742", "cid": "7608017774942683934", "createTime": 1771379707, "createTimeISO": "2026-02-18T01:55:07.000Z", "text": "at that point just get a wii you can do more with it and play bowling🥀💔", "diggCount": 6, "likedByAuthor": false, "pinnedByAuthor": false, "repliesToId": null, "replyCommentTotal": 3, "uid": "7341088531026314283", "uniqueId": "lyz_roblox_", "avatarThumbnail": "https://p16-common-sign.tiktokcdn-us.com/tos-useast8-avt-0068-tx2/22126810127cfe8448dc1f7bbe873101~tplv-tiktokx-cropcenter:100:100.jpg?dr=9640&refresh_token=126af8ed&x-expires=1775750400&x-signature=zHIgrZND2eqDfb9FBW2qtAkAcrY%3D&t=4d5b0474&ps=13740610&shp=30310797&shcp=ff37627b&idc=useast8", "mentions": [], "detailedMentions": [], "text_zh": "那样的话还不如买个Wii，Wii能做的更多，还能玩保龄球🥀💔"}, {"videoWebUrl": "https://www.tiktok.com/@themajorkeyes/video/7605052395382377742", "submittedVideoUrl": "https://www.tiktok.com/@themajorkeyes/video/7605052395382377742", "input": "https://www.tiktok.com/@themajorkeyes/video/7605052395382377742", "cid": "7608664810842981150", "createTime": 1771530346, "createTimeISO": "2026-02-19T19:45:46.000Z", "text": "Just get a Wii at that point", "diggCount": 1, "likedByAuthor": false, "pinnedByAuthor": false, "repliesToId": null, "replyCommentTotal": 1, "uid": "7472590685013181486", "uniqueId": "romec1537", "avatarThumbnail": "https://p16-common-sign.tiktokcdn-us.com/tos-useast8-avt-0068-tx2/fca1abe462e7dd70d5a2ca1f8647441e~tplv-tiktokx-cropcenter:100:100.jpg?dr=9640&refresh_token=4dc0ef5f&x-expires=1775750400&x-signature=uaCYcglM5lnSq2uMm1a8%2FrthJsE%3D&t=4d5b0474&ps=13740610&shp=30310797&shcp=ff37627b&idc=useast8", "mentions": [], "detailedMentions": [], "text_zh": "那时候不如直接买 Wii"}, {"videoWebUrl": "https://www.tiktok.com/@themajorkeyes/video/7605052395382377742", "submittedVideoUrl": "https://www.tiktok.com/@themajorkeyes/video/7605052395382377742", "input": "https://www.tiktok.com/@themajorkeyes/video/7605052395382377742", "cid": "7607959219387876126", "createTime": 1771366061, "createTimeISO": "2026-02-17T22:07:41.000Z", "text": "Same thing 😂", "diggCount": 1, "likedByAuthor": false, "pinnedByAuthor": false, "repliesToId": null, "replyCommentTotal": 3, "uid": "7476552513963574318", "uniqueId": "ashley140804", "avatarThumbnail": "https://p16-common-sign.tiktokcdn-us.com/tos-useast8-avt-0068-tx2/1e3e98074ce13b3857567833f7aefc44~tplv-tiktokx-cropcenter:100:100.jpg?dr=9640&refresh_token=5864383b&x-expires=1775750400&x-signature=e6lC6OTdpTfr%2BD3IggoZ55kNsPM%3D&t=4d5b0474&ps=13740610&shp=30310797&shcp=ff37627b&idc=useast8", "mentions": [], "detailedMentions": [], "text_zh": "一样的啦 😂"}, {"videoWebUrl": "https://www.tiktok.com/@themajorkeyes/video/7605052395382377742", "submittedVideoUrl": "https://www.tiktok.com/@themajorkeyes/video/7605052395382377742", "input": "https://www.tiktok.com/@themajorkeyes/video/7605052395382377742", "cid": "7607909644728419085", "createTime": 1771354533, "createTimeISO": "2026-02-17T18:55:33.000Z", "text": "cool kids", "diggCount": 1, "likedByAuthor": false, "pinnedByAuthor": false, "repliesToId": null, "replyCommentTotal": 5, "uid": "7500422702865744939", "uniqueId": "darnell.lee.spenc", "avatarThumbnail": "https://p16-common-sign.tiktokcdn-us.com/tos-useast5-avt-0068-tx/0a7b8babd6c21827894f2e5462c35058~tplv-tiktokx-cropcenter:100:100.jpg?dr=9640&refresh_token=786d1798&x-expires=1775750400&x-signature=sNCfCjNf%2BFrW02dJUVb5xdv6Q2o%3D&t=4d5b0474&ps=13740610&shp=30310797&shcp=ff37627b&idc=useast8", "mentions": [], "detailedMentions": [], "text_zh": "酷小孩"}, {"videoWebUrl": "https://www.tiktok.com/@themajorkeyes/video/7605052395382377742", "submittedVideoUrl": "https://www.tiktok.com/@themajorkeyes/video/7605052395382377742", "input": "https://www.tiktok.com/@themajorkeyes/video/7605052395382377742", "cid": "7608117329968415502", "createTime": 1771402921, "createTimeISO": "2026-02-18T08:22:01.000Z", "text": "is a remake of the Wii", "diggCount": 1, "likedByAuthor": false, "pinnedByAuthor": false, "repliesToId": null, "replyCommentTotal": 5, "uid": "7204243660690146346", "uniqueId": "uncletonymontana", "avatarThumbnail": "https://p16-common-sign.tiktokcdn-us.com/tos-useast5-avt-0068-tx/3e2bd2f851539dc3c0c0176a8b2f4ab8~tplv-tiktokx-cropcenter:100:100.jpg?dr=9640&refresh_token=3385b725&x-expires=1775750400&x-signature=iyaw3J5JNTkCnOp%2BrkcmU3CDmFc%3D&t=4d5b0474&ps=13740610&shp=30310797&shcp=ff37627b&idc=useast8", "mentions": [], "detailedMentions": [], "text_zh": "是 Wii 的复刻版"}, {"videoWebUrl": "https://www.tiktok.com/@themajorkeyes/video/7605052395382377742", "submittedVideoUrl": "https://www.tiktok.com/@themajorkeyes/video/7605052395382377742", "input": "https://www.tiktok.com/@themajorkeyes/video/7605052395382377742", "cid": "7608566791695172366", "createTime": 1771507550, "createTimeISO": "2026-02-19T13:25:50.000Z", "text": "Maybe get Wii 😉", "diggCount": 0, "likedByAuthor": false, "pinnedByAuthor": false, "repliesToId": null, "replyCommentTotal": 1, "uid": "6711568251069350918", "uniqueId": "goderek91", "avatarThumbnail": "https://p16-common-sign.tiktokcdn-us.com/tos-maliva-avt-0068/7331507687833927685~tplv-tiktokx-cropcenter:100:100.jpg?dr=9640&refresh_token=34f6a6f1&x-expires=1775750400&x-signature=3z74kC2jhMfPqmpwK9aa6Vc8PtM%3D&t=4d5b0474&ps=13740610&shp=30310797&shcp=ff37627b&idc=useast8", "mentions": [], "detailedMentions": [], "text_zh": "也许可以买个 Wii 😉"}, {"videoWebUrl": "https://www.tiktok.com/@themajorkeyes/video/7605052395382377742", "submittedVideoUrl": "https://www.tiktok.com/@themajorkeyes/video/7605052395382377742", "input": "https://www.tiktok.com/@themajorkeyes/video/7605052395382377742", "cid": "7608683582751539982", "createTime": 1771534717, "createTimeISO": "2026-02-19T20:58:37.000Z", "text": "take them outside play with them but outside and play real not fantacies", "diggCount": 1, "likedByAuthor": false, "pinnedByAuthor": false, "repliesToId": null, "replyCommentTotal": 2, "uid": "6881354111402574854", "uniqueId": "marianoruiz70", "avatarThumbnail": "https://p16-common-sign.tiktokcdn-us.com/tos-useast5-avt-0068-tx/92bbf2ada4376e1fdc5aef2280b3d265~tplv-tiktokx-cropcenter:100:100.jpg?dr=9640&refresh_token=253e8aa2&x-expires=1775750400&x-signature=fgp%2BMkgCR%2B%2BTvPQBNhFi2uiGhIg%3D&t=4d5b0474&ps=13740610&shp=30310797&shcp=ff37627b&idc=useast8", "mentions": [], "detailedMentions": [], "text_zh": "带他们出去玩，跟他们在外面玩，玩真的，不是玩虚的"}, {"videoWebUrl": "https://www.tiktok.com/@themajorkeyes/video/7605052395382377742", "submittedVideoUrl": "https://www.tiktok.com/@themajorkeyes/video/7605052395382377742", "input": "https://www.tiktok.com/@themajorkeyes/video/7605052395382377742", "cid": "7608603187789054751", "createTime": 1771516021, "createTimeISO": "2026-02-19T15:47:01.000Z", "text": "What happened to the other little girls arm?", "diggCount": 1, "likedByAuthor": false, "pinnedByAuthor": false, "repliesToId": null, "replyCommentTotal": 1, "uid": "7203864001582564394", "uniqueId": "patriciagomez8969", "avatarThumbnail": "https://p16-common-sign.tiktokcdn-us.com/tos-useast8-avt-0068-tx2/c11a2349b41cf9ec89682010d2b485b7~tplv-tiktokx-cropcenter:100:100.jpg?dr=9640&refresh_token=ac0a01dc&x-expires=1775750400&x-signature=v6LXzDS%2BbNkcjVE7Jj3Q9u7BdYo%3D&t=4d5b0474&ps=13740610&shp=30310797&shcp=ff37627b&idc=useast8", "mentions": [], "detailedMentions": [], "text_zh": "那个小女孩的另一只胳膊怎么了？"}, {"videoWebUrl": "https://www.tiktok.com/@themajorkeyes/video/7605052395382377742", "submittedVideoUrl": "https://www.tiktok.com/@themajorkeyes/video/7605052395382377742", "input": "https://www.tiktok.com/@themajorkeyes/video/7605052395382377742", "cid": "7608257467378270989", "createTime": 1771435513, "createTimeISO": "2026-02-18T17:25:13.000Z", "text": "Still a screen.", "diggCount": 2, "likedByAuthor": false, "pinnedByAuthor": false, "repliesToId": null, "replyCommentTotal": 1, "uid": "7207659075699049518", "uniqueId": "indigo_drawzzz", "avatarThumbnail": "https://p16-common-sign.tiktokcdn-us.com/tos-useast5-avt-0068-tx/01d8daa8d431a132b9ce7f1ae70dde85~tplv-tiktokx-cropcenter:100:100.jpg?dr=9640&refresh_token=d9e68499&x-expires=1775750400&x-signature=KHkxgjnzw7FMCCamB%2Bl4ByRmy%2Bg%3D&t=4d5b0474&ps=13740610&shp=30310797&shcp=ff37627b&idc=useast8", "mentions": [], "detailedMentions": [], "text_zh": "还是个屏幕。"}, {"videoWebUrl": "https://www.tiktok.com/@themajorkeyes/video/7605052395382377742", "submittedVideoUrl": "https://www.tiktok.com/@themajorkeyes/video/7605052395382377742", "input": "https://www.tiktok.com/@themajorkeyes/video/7605052395382377742", "cid": "7608416934485213965", "createTime": 1771472648, "createTimeISO": "2026-02-19T03:44:08.000Z", "text": "I have it and it is really fun with the subscription", "diggCount": 2, "likedByAuthor": false, "pinnedByAuthor": false, "repliesToId": null, "replyCommentTotal": 1, "uid": "7597248817004823565", "uniqueId": "luna518362", "avatarThumbnail": "https://p19-common-sign.tiktokcdn-us.com/musically-maliva-obj/1594805258216454~tplv-tiktokx-cropcenter:100:100.jpg?dr=9640&refresh_token=73283d13&x-expires=1775750400&x-signature=JuTVwFCkc0o2JQmYrU9PSTZ9%2Fyw%3D&t=4d5b0474&ps=13740610&shp=30310797&shcp=ff37627b&idc=useast8", "mentions": [], "detailedMentions": [], "text_zh": "我也有，订阅后真的很有趣"}, {"videoWebUrl": "https://www.tiktok.com/@themajorkeyes/video/7605052395382377742", "submittedVideoUrl": "https://www.tiktok.com/@themajorkeyes/video/7605052395382377742", "input": "https://www.tiktok.com/@themajorkeyes/video/7605052395382377742", "cid": "7608500281273516830", "createTime": 1771492118, "createTimeISO": "2026-02-19T09:08:38.000Z", "text": "I have that it’s called playground and I play it with my friends", "diggCount": 0, "likedByAuthor": false, "pinnedByAuthor": false, "repliesToId": null, "replyCommentTotal": 1, "uid": "7487365966197392426", "uniqueId": "slayrobloxfits", "avatarThumbnail": "https://p16-common-sign.tiktokcdn-us.com/tos-useast8-avt-0068-tx2/af511901d0ccb3a3e886659de08f83a1~tplv-tiktokx-cropcenter:100:100.jpg?dr=9640&refresh_token=7f618ed0&x-expires=1775750400&x-signature=ru4%2BwEV2NqAv4DLNjNrXAVzOXi8%3D&t=4d5b0474&ps=13740610&shp=30310797&shcp=ff37627b&idc=useast8", "mentions": [], "detailedMentions": [], "text_zh": "我也有那个，叫Playground，我跟朋友一起玩"}, {"videoWebUrl": "https://www.tiktok.com/@themajorkeyes/video/7605052395382377742", "submittedVideoUrl": "https://www.tiktok.com/@themajorkeyes/video/7605052395382377742", "input": "https://www.tiktok.com/@themajorkeyes/video/7605052395382377742", "cid": "7608659949175489311", "createTime": 1771529231, "createTimeISO": "2026-02-19T19:27:11.000Z", "text": "I think the point was spending time together, yall", "diggCount": 0, "likedByAuthor": false, "pinnedByAuthor": false, "repliesToId": null, "replyCommentTotal": 1, "uid": "7587237576471135245", "uniqueId": "artificial_fl4vor", "avatarThumbnail": "https://p16-common-sign.tiktokcdn-us.com/tos-useast8-avt-0068-tx2/a06e31832be37e6427015fa6bed840f4~tplv-tiktokx-cropcenter:100:100.jpg?dr=9640&refresh_token=b4fbb949&x-expires=1775750400&x-signature=VXHwuQCBmF%2BfuB%2BrzABV6DC4nuc%3D&t=4d5b0474&ps=13740610&shp=30310797&shcp=ff37627b&idc=useast8", "mentions": [], "detailedMentions": [], "text_zh": "我觉得重点是大家一起玩，你们"}, {"videoWebUrl": "https://www.tiktok.com/@themajorkeyes/video/7605052395382377742", "submittedVideoUrl": "https://www.tiktok.com/@themajorkeyes/video/7605052395382377742", "input": "https://www.tiktok.com/@themajorkeyes/video/7605052395382377742", "cid": "7608782823265714957", "createTime": 1771557838, "createTimeISO": "2026-02-20T03:23:58.000Z", "text": "It’s still a screen.", "diggCount": 1, "likedByAuthor": false, "pinnedByAuthor": false, "repliesToId": null, "replyCommentTotal": 1, "uid": "7123986579946783790", "uniqueId": "amyomayra_", "avatarThumbnail": "https://p16-common-sign.tiktokcdn-us.com/tos-useast5-avt-0068-tx/a278cfe63a65733dc4220ee40a711d00~tplv-tiktokx-cropcenter:100:100.jpg?dr=9640&refresh_token=6e76ad5e&x-expires=1775750400&x-signature=slpR242kPJhJm%2FjWSbL%2BFMhjZbw%3D&t=4d5b0474&ps=13740610&shp=30310797&shcp=ff37627b&idc=useast8", "mentions": [], "detailedMentions": [], "text_zh": "它还是个屏幕。"}, {"videoWebUrl": "https://www.tiktok.com/@themajorkeyes/video/7605052395382377742", "submittedVideoUrl": "https://www.tiktok.com/@themajorkeyes/video/7605052395382377742", "input": "https://www.tiktok.com/@themajorkeyes/video/7605052395382377742", "cid": "7609045940251411214", "createTime": 1771619100, "createTimeISO": "2026-02-20T20:25:00.000Z", "text": "Their having family time", "diggCount": 0, "likedByAuthor": false, "pinnedByAuthor": false, "repliesToId": null, "replyCommentTotal": 1, "uid": "7587948744910341134", "uniqueId": "5starr_xalah", "avatarThumbnail": "https://p16-common-sign.tiktokcdn-us.com/tos-useast5-avt-0068-tx/0e1ba54bf107d6066b9cbd8359eaa708~tplv-tiktokx-cropcenter:100:100.jpg?dr=9640&refresh_token=bce1e166&x-expires=1775750400&x-signature=MoynW3jbaVsfPoY6WxAbIcDceUA%3D&t=4d5b0474&ps=13740610&shp=30310797&shcp=ff37627b&idc=useast8", "mentions": [], "detailedMentions": [], "text_zh": "他们在享受家庭时光"}, {"videoWebUrl": "https://www.tiktok.com/@themajorkeyes/video/7605052395382377742", "submittedVideoUrl": "https://www.tiktok.com/@themajorkeyes/video/7605052395382377742", "input": "https://www.tiktok.com/@themajorkeyes/video/7605052395382377742", "cid": "7608588799782961934", "createTime": 1771512701, "createTimeISO": "2026-02-19T14:51:41.000Z", "text": "Looks fun. We still have bowling alleys and game boards at the kitchen table 😂🥰", "diggCount": 0, "likedByAuthor": false, "pinnedByAuthor": false, "repliesToId": null, "replyCommentTotal": 1, "uid": "6868595546375422981", "uniqueId": "kim10.15", "avatarThumbnail": "https://p16-common-sign.tiktokcdn-us.com/musically-maliva-obj/1594805258216454~tplv-tiktokx-cropcenter:100:100.jpg?dr=9640&refresh_token=5ac77edb&x-expires=1775750400&x-signature=8BQcHxXTCDjGwd5u85GfrhlwzQw%3D&t=4d5b0474&ps=13740610&shp=30310797&shcp=ff37627b&idc=useast8", "mentions": [], "detailedMentions": [], "text_zh": "看起来很好玩。我们家还有保龄球馆和餐桌上的棋盘游戏 😂🥰"}, {"videoWebUrl": "https://www.tiktok.com/@themajorkeyes/video/7605052395382377742", "submittedVideoUrl": "https://www.tiktok.com/@themajorkeyes/video/7605052395382377742", "input": "https://www.tiktok.com/@themajorkeyes/video/7605052395382377742", "cid": "7608929942223831838", "createTime": 1771592133, "createTimeISO": "2026-02-20T12:55:33.000Z", "text": "I still see a screen", "diggCount": 1, "likedByAuthor": false, "pinnedByAuthor": false, "repliesToId": null, "replyCommentTotal": 1, "uid": "6775320016382755845", "uniqueId": "uridol_number1", "avatarThumbnail": "https://p16-common-sign.tiktokcdn-us.com/tos-useast5-avt-0068-tx/f1e1303622a7b3773e6794746cd33e30~tplv-tiktokx-cropcenter:100:100.jpg?dr=9640&refresh_token=0ff6f04e&x-expires=1775750400&x-signature=pS7Uuw1ZCgtU%2B3LhNEHLLzSjnIY%3D&t=4d5b0474&ps=13740610&shp=30310797&shcp=ff37627b&idc=useast8", "mentions": [], "detailedMentions": [], "text_zh": "我还是看到了屏幕"}, {"videoWebUrl": "https://www.tiktok.com/@themajorkeyes/video/7605052395382377742", "submittedVideoUrl": "https://www.tiktok.com/@themajorkeyes/video/7605052395382377742", "input": "https://www.tiktok.com/@themajorkeyes/video/7605052395382377742", "cid": "7608291582391943949", "createTime": 1771443460, "createTimeISO": "2026-02-18T19:37:40.000Z", "text": "Is this free after gettythe box?", "diggCount": 0, "likedByAuthor": false, "pinnedByAuthor": false, "repliesToId": null, "replyCommentTotal": 1, "uid": "7012070678367798278", "uniqueId": "pricelexali8", "avatarThumbnail": "https://p16-common-sign.tiktokcdn-us.com/tos-useast5-avt-0068-tx/35714698896506aec159fa8cf140db20~tplv-tiktokx-cropcenter:100:100.jpg?dr=9640&refresh_token=88213556&x-expires=1775750400&x-signature=axgw8Dg8o5%2FdtVyZo1oeHvZKvz8%3D&t=4d5b0474&ps=13740610&shp=30310797&shcp=ff37627b&idc=useast8", "mentions": [], "detailedMentions": [], "text_zh": "拿到盒子之后游戏是免费的吗？"}, {"videoWebUrl": "https://www.tiktok.com/@themajorkeyes/video/7605052395382377742", "submittedVideoUrl": "https://www.tiktok.com/@themajorkeyes/video/7605052395382377742", "input": "https://www.tiktok.com/@themajorkeyes/video/7605052395382377742", "cid": "7608246160998056718", "createTime": 1771432873, "createTimeISO": "2026-02-18T16:41:13.000Z", "text": "My Daughter bought one and they definitely have great Family time together", "diggCount": 2, "likedByAuthor": false, "pinnedByAuthor": false, "repliesToId": null, "replyCommentTotal": 1, "uid": "6831585942828090373", "uniqueId": "carolynhatfield71", "avatarThumbnail": "https://p16-common-sign.tiktokcdn-us.com/tos-maliva-avt-0068/7329904844752502789~tplv-tiktokx-cropcenter:100:100.jpg?dr=9640&refresh_token=126d7ce5&x-expires=1775750400&x-signature=27qnjytw%2Bw9YdHIowIl81xfR8Pw%3D&t=4d5b0474&ps=13740610&shp=30310797&shcp=ff37627b&idc=useast8", "mentions": [], "detailedMentions": [], "text_zh": "我女儿买了，她们一起度过了很棒的家庭时光"}, {"videoWebUrl": "https://www.tiktok.com/@themajorkeyes/video/7605052395382377742", "submittedVideoUrl": "https://www.tiktok.com/@themajorkeyes/video/7605052395382377742", "input": "https://www.tiktok.com/@themajorkeyes/video/7605052395382377742", "cid": "7605057172745634591", "createTime": 1770690396, "createTimeISO": "2026-02-10T02:26:36.000Z", "text": "First! And where can you get this game?", "diggCount": 1, "likedByAuthor": false, "pinnedByAuthor": false, "repliesToId": null, "replyCommentTotal": 2, "uid": "7373520110555251758", "uniqueId": "fav.cruisenye316", "avatarThumbnail": "https://p16-common-sign.tiktokcdn-us.com/tos-useast8-avt-0068-tx2/365e0bb9117139ae49b333c2806a99dc~tplv-tiktokx-cropcenter:100:100.jpg?dr=9640&refresh_token=b389c80f&x-expires=1775750400&x-signature=Q4QEVwTCadxVmMjKlOFhVe3lNWI%3D&t=4d5b0474&ps=13740610&shp=30310797&shcp=ff37627b&idc=useast8", "mentions": [], "detailedMentions": [], "text_zh": "第一个！这游戏在哪儿能买到？"}, {"videoWebUrl": "https://www.tiktok.com/@themajorkeyes/video/7605052395382377742", "submittedVideoUrl": "https://www.tiktok.com/@themajorkeyes/video/7605052395382377742", "input": "https://www.tiktok.com/@themajorkeyes/video/7605052395382377742", "cid": "7608034750238851853", "createTime": 1771383651, "createTimeISO": "2026-02-18T03:00:51.000Z", "text": "I got that", "diggCount": 1, "likedByAuthor": false, "pinnedByAuthor": false, "repliesToId": null, "replyCommentTotal": 1, "uid": "7403811677417243690", "uniqueId": "promysswalker0", "avatarThumbnail": "https://p16-common-sign.tiktokcdn-us.com/tos-useast5-avt-0068-tx/7dd324a2d6cabfea281300cdae7076b9~tplv-tiktokx-cropcenter:100:100.jpg?dr=9640&refresh_token=ca1179a2&x-expires=1775750400&x-signature=dJU68UQRVYKUuCdm%2B2b6UsWQzNI%3D&t=4d5b0474&ps=13740610&shp=30310797&shcp=ff37627b&idc=useast8", "mentions": [], "detailedMentions": [], "text_zh": "我买了"}, {"videoWebUrl": "https://www.tiktok.com/@themajorkeyes/video/7605052395382377742", "submittedVideoUrl": "https://www.tiktok.com/@themajorkeyes/video/7605052395382377742", "input": "https://www.tiktok.com/@themajorkeyes/video/7605052395382377742", "cid": "7608522629183505183", "createTime": 1771497311, "createTimeISO": "2026-02-19T10:35:11.000Z", "text": "Almost all the games in here are things you can do in real life instead of using the tv?", "diggCount": 1, "likedByAuthor": false, "pinnedByAuthor": false, "repliesToId": null, "replyCommentTotal": 1, "uid": "7582710128261268494", "uniqueId": "jevil0912", "avatarThumbnail": "https://p16-common-sign.tiktokcdn-us.com/tos-useast8-avt-0068-tx2/603b4d5329748aa44be42a77ec38c9da~tplv-tiktokx-cropcenter:100:100.jpg?dr=9640&refresh_token=59d60efe&x-expires=1775750400&x-signature=sJauEK%2BleYvea7dikSGhDptOk%2FE%3D&t=4d5b0474&ps=13740610&shp=30310797&shcp=ff37627b&idc=useast8", "mentions": [], "detailedMentions": [], "text_zh": "这里面的游戏几乎都能在现实生活中做，而不是对着电视玩？"}, {"videoWebUrl": "https://www.tiktok.com/@themajorkeyes/video/7605052395382377742", "submittedVideoUrl": "https://www.tiktok.com/@themajorkeyes/video/7605052395382377742", "input": "https://www.tiktok.com/@themajorkeyes/video/7605052395382377742", "cid": "7608265921802584863", "createTime": 1771437481, "createTimeISO": "2026-02-18T17:58:01.000Z", "text": "Family time is always important, We bought this for our grandkids to play on the weekend after all homework assignments are done !!", "diggCount": 1, "likedByAuthor": false, "pinnedByAuthor": false, "repliesToId": null, "replyCommentTotal": 1, "uid": "7341540577789985834", "uniqueId": "move.in.silence50", "avatarThumbnail": "https://p16-common-sign.tiktokcdn-us.com/musically-maliva-obj/1594805258216454~tplv-tiktokx-cropcenter:100:100.jpg?dr=9640&refresh_token=5ac77edb&x-expires=1775750400&x-signature=8BQcHxXTCDjGwd5u85GfrhlwzQw%3D&t=4d5b0474&ps=13740610&shp=30310797&shcp=ff37627b&idc=useast8", "mentions": [], "detailedMentions": [], "text_zh": "家庭时光总是很重要，我们给孙子孙女们买了让他们周末写完作业后玩！！"}, {"videoWebUrl": "https://www.tiktok.com/@themajorkeyes/video/7605052395382377742", "submittedVideoUrl": "https://www.tiktok.com/@themajorkeyes/video/7605052395382377742", "input": "https://www.tiktok.com/@themajorkeyes/video/7605052395382377742", "cid": "7608499409479320333", "createTime": 1771491905, "createTimeISO": "2026-02-19T09:05:05.000Z", "text": "we got one of these for Christmas and man it is FUNNNNN", "diggCount": 1, "likedByAuthor": false, "pinnedByAuthor": false, "repliesToId": null, "replyCommentTotal": 1, "uid": "7310955493512889386", "uniqueId": "irox5523", "avatarThumbnail": "https://p16-common-sign.tiktokcdn-us.com/tos-useast5-avt-0068-tx/627b5a131f2a99788c2bc2ed20d29658~tplv-tiktokx-cropcenter:100:100.jpg?dr=9640&refresh_token=05c1c735&x-expires=1775750400&x-signature=6H8Aq2otpWqsKFrsH0CVcE1Z3vg%3D&t=4d5b0474&ps=13740610&shp=30310797&shcp=ff37627b&idc=useast8", "mentions": [], "detailedMentions": [], "text_zh": "圣诞节我们收到了一个这个，天呐，太好玩了！"}, {"videoWebUrl": "https://www.tiktok.com/@themajorkeyes/video/7605052395382377742", "submittedVideoUrl": "https://www.tiktok.com/@themajorkeyes/video/7605052395382377742", "input": "https://www.tiktok.com/@themajorkeyes/video/7605052395382377742", "cid": "7608016505045091103", "createTime": 1771379401, "createTimeISO": "2026-02-18T01:50:01.000Z", "text": "Jesus loves you!🫶🏼", "diggCount": 3, "likedByAuthor": false, "pinnedByAuthor": false, "repliesToId": null, "replyCommentTotal": 0, "uid": "6646469490686099462", "uniqueId": "haylieghhhh", "avatarThumbnail": "https://p16-common-sign.tiktokcdn-us.com/tos-useast5-avt-0068-tx/7351171888283910186~tplv-tiktokx-cropcenter:100:100.jpg?dr=9640&refresh_token=7a7e6b9e&x-expires=1775750400&x-signature=N4y4Q24J5T5clXzLGphqXob4vy4%3D&t=4d5b0474&ps=13740610&shp=30310797&shcp=ff37627b&idc=useast8", "mentions": [], "detailedMentions": [], "text_zh": "耶稣爱你！🫶🏼"}, {"videoWebUrl": "https://www.tiktok.com/@themajorkeyes/video/7605052395382377742", "submittedVideoUrl": "https://www.tiktok.com/@themajorkeyes/video/7605052395382377742", "input": "https://www.tiktok.com/@themajorkeyes/video/7605052395382377742", "cid": "7608378657975812878", "createTime": 1771463737, "createTimeISO": "2026-02-19T01:15:37.000Z", "text": "is there a monthly fee for the play pass?", "diggCount": 0, "likedByAuthor": false, "pinnedByAuthor": false, "repliesToId": null, "replyCommentTotal": 1, "uid": "7068263254960325679", "uniqueId": "pattie805", "avatarThumbnail": "https://p16-common-sign.tiktokcdn-us.com/tos-useast5-avt-0068-tx/7352493977829900330~tplv-tiktokx-cropcenter:100:100.jpg?dr=9640&refresh_token=48210b61&x-expires=1775750400&x-signature=%2Fq5V2daOAdXyn3xxBypyd2K6h6Q%3D&t=4d5b0474&ps=13740610&shp=30310797&shcp=ff37627b&idc=useast8", "mentions": [], "detailedMentions": [], "text_zh": "玩这个需要月费吗？"}, {"videoWebUrl": "https://www.tiktok.com/@themajorkeyes/video/7605052395382377742", "submittedVideoUrl": "https://www.tiktok.com/@themajorkeyes/video/7605052395382377742", "input": "https://www.tiktok.com/@themajorkeyes/video/7605052395382377742", "cid": "7608315859937002270", "createTime": 1771449102, "createTimeISO": "2026-02-18T21:11:42.000Z", "text": "Just buy a switch 🥀", "diggCount": 0, "likedByAuthor": false, "pinnedByAuthor": false, "repliesToId": null, "replyCommentTotal": 1, "uid": "7385308542632903722", "uniqueId": "tapir4227", "avatarThumbnail": "https://p16-common-sign.tiktokcdn-us.com/tos-useast8-avt-0068-tx2/efaef49f52bcad7256c2c5c966b07f4c~tplv-tiktokx-cropcenter:100:100.jpg?dr=9640&refresh_token=35bc314a&x-expires=1775750400&x-signature=wyelnWHid7DqJjHnouxuWwJSNqA%3D&t=4d5b0474&ps=13740610&shp=30310797&shcp=ff37627b&idc=useast8", "mentions": [], "detailedMentions": [], "text_zh": "直接买个 Switch 吧 🥀"}, {"videoWebUrl": "https://www.tiktok.com/@themajorkeyes/video/7605052395382377742", "submittedVideoUrl": "https://www.tiktok.com/@themajorkeyes/video/7605052395382377742", "input": "https://www.tiktok.com/@themajorkeyes/video/7605052395382377742", "cid": "7607913237909291806", "createTime": 1771355366, "createTimeISO": "2026-02-17T19:09:26.000Z", "text": "I have one", "diggCount": 2, "likedByAuthor": false, "pinnedByAuthor": false, "repliesToId": null, "replyCommentTotal": 1, "uid": "7049751374188708870", "uniqueId": "kueenkemari1517", "avatarThumbnail": "https://p16-common-sign.tiktokcdn-us.com/tos-useast8-avt-0068-tx2/3176a14b9d48a9b512c779d796550849~tplv-tiktokx-cropcenter:100:100.jpg?dr=9640&refresh_token=11a2c482&x-expires=1775750400&x-signature=FUY6Vzh8E2pXCiD4uH70d5hhBtM%3D&t=4d5b0474&ps=13740610&shp=30310797&shcp=ff37627b&idc=useast8", "mentions": [], "detailedMentions": [], "text_zh": "我有一个"}, {"videoWebUrl": "https://www.tiktok.com/@themajorkeyes/video/7605052395382377742", "submittedVideoUrl": "https://www.tiktok.com/@themajorkeyes/video/7605052395382377742", "input": "https://www.tiktok.com/@themajorkeyes/video/7605052395382377742", "cid": "7608546880653968142", "createTime": 1771502956, "createTimeISO": "2026-02-19T12:09:16.000Z", "text": "I look at the caption", "diggCount": 1, "likedByAuthor": true, "pinnedByAuthor": false, "repliesToId": null, "replyCommentTotal": 0, "uid": "7600985397493842958", "uniqueId": "stell4r_st4r", "avatarThumbnail": "https://p16-common-sign.tiktokcdn-us.com/tos-useast5-avt-0068-tx/135e13ab63b80df7856d9ae5b29ce269~tplv-tiktokx-cropcenter:100:100.jpg?dr=9640&refresh_token=8dbf4148&x-expires=1775750400&x-signature=93%2BtBYHu%2B3TcAGaxB8jlrb%2Fk5dU%3D&t=4d5b0474&ps=13740610&shp=30310797&shcp=ff37627b&idc=useast8", "mentions": [], "detailedMentions": [], "text_zh": "我看了标题"}, {"videoWebUrl": "https://www.tiktok.com/@themajorkeyes/video/7605052395382377742", "submittedVideoUrl": "https://www.tiktok.com/@themajorkeyes/video/7605052395382377742", "input": "https://www.tiktok.com/@themajorkeyes/video/7605052395382377742", "cid": "7608734496532628237", "createTime": 1771546589, "createTimeISO": "2026-02-20T00:16:29.000Z", "text": "If u melt ice it becomes water ah video", "diggCount": 0, "likedByAuthor": false, "pinnedByAuthor": false, "repliesToId": null, "replyCommentTotal": 0, "uid": "7574645255737574414", "uniqueId": "ankylosaurs13", "avatarThumbnail": "https://p16-common-sign.tiktokcdn-us.com/tos-useast5-avt-0068-tx/0ea355c3ddf54e3c24111eefb692234a~tplv-tiktokx-cropcenter:100:100.jpg?dr=9640&refresh_token=54edd306&x-expires=1775750400&x-signature=5bBenrB9%2BfKEqHOe9RGzf1b1vSI%3D&t=4d5b0474&ps=13740610&shp=30310797&shcp=ff37627b&idc=useast5", "mentions": [], "detailedMentions": [], "text_zh": "如果你融化冰，它就会变成水，哇，视频"}, {"videoWebUrl": "https://www.tiktok.com/@themajorkeyes/video/7605052395382377742", "submittedVideoUrl": "https://www.tiktok.com/@themajorkeyes/video/7605052395382377742", "input": "https://www.tiktok.com/@themajorkeyes/video/7605052395382377742", "cid": "7608759274786112270", "createTime": 1771552371, "createTimeISO": "2026-02-20T01:52:51.000Z", "text": "Es lo mismo", "diggCount": 0, "likedByAuthor": false, "pinnedByAuthor": false, "repliesToId": null, "replyCommentTotal": 0, "uid": "7160526777678054446", "uniqueId": "rosaderobles168", "avatarThumbnail": "https://p16-common-sign.tiktokcdn-us.com/tos-useast5-avt-0068-tx/3d31fb91ca5dd46268b19c4cb78174ed~tplv-tiktokx-cropcenter:100:100.jpg?dr=9640&refresh_token=3c710232&x-expires=1775750400&x-signature=DVIiXCcN04bD1ILzeVLwRrDGbWI%3D&t=4d5b0474&ps=13740610&shp=30310797&shcp=ff37627b&idc=useast5", "mentions": [], "detailedMentions": [], "text_zh": "是差不多的意思"}, {"videoWebUrl": "https://www.tiktok.com/@themajorkeyes/video/7605052395382377742", "submittedVideoUrl": "https://www.tiktok.com/@themajorkeyes/video/7605052395382377742", "input": "https://www.tiktok.com/@themajorkeyes/video/7605052395382377742", "cid": "7609003059985515295", "createTime": 1771609129, "createTimeISO": "2026-02-20T17:38:49.000Z", "text": "333", "diggCount": 0, "likedByAuthor": false, "pinnedByAuthor": false, "repliesToId": null, "replyCommentTotal": 0, "uid": "7564258447447262222", "uniqueId": "dom92928", "avatarThumbnail": "https://p16-common-sign.tiktokcdn-us.com/tos-useast8-avt-0068-tx2/45aa16394788c2e7006c8b36a6a02d46~tplv-tiktokx-cropcenter:100:100.jpg?dr=9640&refresh_token=da0a08ae&x-expires=1775750400&x-signature=tkXTqoaovbvV5%2FFzrq0RsOlNLVo%3D&t=4d5b0474&ps=13740610&shp=30310797&shcp=ff37627b&idc=useast5", "mentions": [], "detailedMentions": [], "text_zh": "333"}, {"videoWebUrl": "https://www.tiktok.com/@themajorkeyes/video/7605052395382377742", "submittedVideoUrl": "https://www.tiktok.com/@themajorkeyes/video/7605052395382377742", "input": "https://www.tiktok.com/@themajorkeyes/video/7605052395382377742", "cid": "7607933659651916558", "createTime": 1771360143, "createTimeISO": "2026-02-17T20:29:03.000Z", "text": "No don’t police them on electronics just make sure they do skincare and workout and do cardio every day", "diggCount": 0, "likedByAuthor": false, "pinnedByAuthor": false, "repliesToId": null, "replyCommentTotal": 0, "uid": "7241820289885357098", "uniqueId": "hoophug9", "avatarThumbnail": "https://p16-common-sign.tiktokcdn-us.com/tos-useast5-avt-0068-tx/794bedd1fd2b9ca2c8fa46e4d5e014d1~tplv-tiktokx-cropcenter:100:100.jpg?dr=9640&refresh_token=dc77dc43&x-expires=1775750400&x-signature=3%2BxNGeKJD1yOOiESP%2Bjcf0hqhjw%3D&t=4d5b0474&ps=13740610&shp=30310797&shcp=ff37627b&idc=useast5", "mentions": [], "detailedMentions": [], "text_zh": "别在电子产品上管他们，只要确保他们每天都做护肤、锻炼和有氧运动就行"}, {"videoWebUrl": "https://www.tiktok.com/@themajorkeyes/video/7605052395382377742", "submittedVideoUrl": "https://www.tiktok.com/@themajorkeyes/video/7605052395382377742", "input": "https://www.tiktok.com/@themajorkeyes/video/7605052395382377742", "cid": "7608335131876836126", "createTime": 1771453611, "createTimeISO": "2026-02-18T22:26:51.000Z", "text": "Something called a Wii", "diggCount": 1, "likedByAuthor": false, "pinnedByAuthor": false, "repliesToId": null, "replyCommentTotal": 1, "uid": "7484770332689941550", "uniqueId": "butterball_278", "avatarThumbnail": "https://p16-common-sign.tiktokcdn-eu.com/tos-maliva-avt-0068/d27fc303e71befaf337700f209be2122~tplv-tiktokx-cropcenter:100:100.jpg?dr=10399&refresh_token=62b5c722&x-expires=1775750400&x-signature=cBDvT21mdnonz%2FYbI%2FMdphXSx8g%3D&t=4d5b0474&ps=13740610&shp=30310797&shcp=ff37627b&idc=no1a", "mentions": [], "detailedMentions": [], "text_zh": "一个叫 Wii 的东西"}, {"videoWebUrl": "https://www.tiktok.com/@themajorkeyes/video/7605052395382377742", "submittedVideoUrl": "https://www.tiktok.com/@themajorkeyes/video/7605052395382377742", "input": "https://www.tiktok.com/@themajorkeyes/video/7605052395382377742", "cid": "7607863121922851597", "createTime": 1771343704, "createTimeISO": "2026-02-17T15:55:04.000Z", "text": "that looks boring i will never do that to my kids when i grow up", "diggCount": 4, "likedByAuthor": false, "pinnedByAuthor": false, "repliesToId": null, "replyCommentTotal": 2, "uid": "7458474317488260138", "uniqueId": "forverfriends3", "avatarThumbnail": "https://p16-common-sign.tiktokcdn-eu.com/tos-maliva-avt-0068/559f7f2a1ba5b8376035dbb7a3ded1fb~tplv-tiktokx-cropcenter:100:100.jpg?dr=10399&refresh_token=e46d924e&x-expires=1775750400&x-signature=FKfq1KQVopNzNAiGo7lZJW7ZPSg%3D&t=4d5b0474&ps=13740610&shp=30310797&shcp=ff37627b&idc=no1a", "mentions": [], "detailedMentions": [], "text_zh": "这看起来好无聊，我长大了绝不会让我孩子这样"}, {"videoWebUrl": "https://www.tiktok.com/@themajorkeyes/video/7605052395382377742", "submittedVideoUrl": "https://www.tiktok.com/@themajorkeyes/video/7605052395382377742", "input": "https://www.tiktok.com/@themajorkeyes/video/7605052395382377742", "cid": "7608230371080061709", "createTime": 1771429218, "createTimeISO": "2026-02-18T15:40:18.000Z", "text": "I need one of these for my babies. It’s basically the wii 😂", "diggCount": 0, "likedByAuthor": false, "pinnedByAuthor": false, "repliesToId": null, "replyCommentTotal": 1, "uid": "7100714872753226795", "uniqueId": "congamer95", "avatarThumbnail": "https://p16-common-sign.tiktokcdn-eu.com/tos-maliva-avt-0068/64c6e847840afdc6571749524c63ad64~tplv-tiktokx-cropcenter:100:100.jpg?dr=10399&refresh_token=005b3b0b&x-expires=1775750400&x-signature=eXE8HrKBO3KVEmj0%2FFsk5stboEE%3D&t=4d5b0474&ps=13740610&shp=30310797&shcp=ff37627b&idc=no1a", "mentions": [], "detailedMentions": [], "text_zh": "我得给我家宝贝们来一个。这基本上就是 Wii 😂"}, {"videoWebUrl": "https://www.tiktok.com/@themajorkeyes/video/7605052395382377742", "submittedVideoUrl": "https://www.tiktok.com/@themajorkeyes/video/7605052395382377742", "input": "https://www.tiktok.com/@themajorkeyes/video/7605052395382377742", "cid": "7607991115950801694", "createTime": 1771373497, "createTimeISO": "2026-02-18T00:11:37.000Z", "text": "My family also has a playground and we love it🥰 I love to play on it and it’s so fun. I love the bowling game. It’s my favorite game.", "diggCount": 0, "likedByAuthor": false, "pinnedByAuthor": false, "repliesToId": null, "replyCommentTotal": 1, "uid": "7576347973224170509", "uniqueId": "serenit890", "avatarThumbnail": "https://p19-common-sign.tiktokcdn-eu.com/tos-maliva-avt-0068/6eacbae993c23b7ba7214aedd3738df5~tplv-tiktokx-cropcenter:100:100.jpg?dr=10399&refresh_token=85f92ae0&x-expires=1775750400&x-signature=PClenCG%2FKEea0n5gqwxjnTrBzYo%3D&t=4d5b0474&ps=13740610&shp=30310797&shcp=ff37627b&idc=no1a", "mentions": [], "detailedMentions": [], "text_zh": "我家也有一个游乐场，我们很喜欢🥰 我喜欢在上面玩，太好玩了。我喜欢保龄球游戏，那是我最喜欢的游戏。"}, {"videoWebUrl": "https://www.tiktok.com/@themajorkeyes/video/7605052395382377742", "submittedVideoUrl": "https://www.tiktok.com/@themajorkeyes/video/7605052395382377742", "input": "https://www.tiktok.com/@themajorkeyes/video/7605052395382377742", "cid": "7608695773500310302", "createTime": 1771537556, "createTimeISO": "2026-02-19T21:45:56.000Z", "text": "what happened to her arm I like that cast", "diggCount": 0, "likedByAuthor": false, "pinnedByAuthor": false, "repliesToId": null, "replyCommentTotal": 1, "uid": "7142115312594060334", "uniqueId": "jessey1228", "avatarThumbnail": "https://p16-common-sign.tiktokcdn-eu.com/tos-maliva-avt-0068/7337811180067258410~tplv-tiktokx-cropcenter:100:100.jpg?dr=10399&refresh_token=295b3c88&x-expires=1775750400&x-signature=roKflhDlTuoKxceRvIrj6LWaBC4%3D&t=4d5b0474&ps=13740610&shp=30310797&shcp=ff37627b&idc=no1a", "mentions": [], "detailedMentions": [], "text_zh": "她胳膊怎么了？我喜欢那个石膏"}, {"videoWebUrl": "https://www.tiktok.com/@themajorkeyes/video/7605052395382377742", "submittedVideoUrl": "https://www.tiktok.com/@themajorkeyes/video/7605052395382377742", "input": "https://www.tiktok.com/@themajorkeyes/video/7605052395382377742", "cid": "7607862306722480916", "createTime": 1771343486, "createTimeISO": "2026-02-17T15:51:26.000Z", "text": "😅😅😅😅😅😅", "diggCount": 0, "likedByAuthor": false, "pinnedByAuthor": false, "repliesToId": null, "replyCommentTotal": 0, "uid": "7527006853084873784", "uniqueId": "user4374304683139", "avatarThumbnail": "https://p16-common-sign.tiktokcdn-us.com/tos-maliva-avt-0068/aff86f30c396918e971023dfb3bddbaf~tplv-tiktokx-cropcenter:100:100.jpg?dr=9640&refresh_token=49dd30f1&x-expires=1775750400&x-signature=bZ%2FXUhYJNTrqzV4iYQtbMLfcIL0%3D&t=4d5b0474&ps=13740610&shp=30310797&shcp=ff37627b&idc=useast8", "mentions": [], "detailedMentions": [], "text_zh": "😅😅😅😅😅😅"}, {"videoWebUrl": "https://www.tiktok.com/@themajorkeyes/video/7605052395382377742", "submittedVideoUrl": "https://www.tiktok.com/@themajorkeyes/video/7605052395382377742", "input": "https://www.tiktok.com/@themajorkeyes/video/7605052395382377742", "cid": "7608301184624935693", "createTime": 1771445686, "createTimeISO": "2026-02-18T20:14:46.000Z", "text": "🌍🩷🩷🩷🩷✝️🫂🛐💙🙏🏽🙏🙏🏻🙏🏾🙏🏿", "diggCount": 0, "likedByAuthor": false, "pinnedByAuthor": false, "repliesToId": null, "replyCommentTotal": 0, "uid": "7198364759704863790", "uniqueId": "belenalvarez221", "avatarThumbnail": "https://p16-common-sign.tiktokcdn-us.com/tos-useast5-avt-0068-tx/7198388163071442986~tplv-tiktokx-cropcenter:100:100.jpg?dr=9640&refresh_token=99670711&x-expires=1775750400&x-signature=yDxQTNpALgpy4qXQt5NPL5wPYRU%3D&t=4d5b0474&ps=13740610&shp=30310797&shcp=ff37627b&idc=useast8", "mentions": [], "detailedMentions": [], "text_zh": "🌍🩷🩷🩷🩷✝️🫂🛐💙🙏🏽🙏🙏🏻🙏🏾🙏🏿"}, {"videoWebUrl": "https://www.tiktok.com/@themajorkeyes/video/7605052395382377742", "submittedVideoUrl": "https://www.tiktok.com/@themajorkeyes/video/7605052395382377742", "input": "https://www.tiktok.com/@themajorkeyes/video/7605052395382377742", "cid": "7608701966416544532", "createTime": 1771539000, "createTimeISO": "2026-02-19T22:10:00.000Z", "text": "❤️😍", "diggCount": 0, "likedByAuthor": false, "pinnedByAuthor": false, "repliesToId": null, "replyCommentTotal": 0, "uid": "7591486572659852344", "uniqueId": "aliisasa.aliisasa", "avatarThumbnail": "https://p19-common-sign.tiktokcdn-us.com/tos-alisg-avt-0068/a5588b9e2ff5c4964eaf44949aba0ba7~tplv-tiktokx-cropcenter:100:100.jpg?dr=9640&refresh_token=d7672b4a&x-expires=1775750400&x-signature=fXP%2FGzjUmA7Kxg%2B3G3ehjSKSsB4%3D&t=4d5b0474&ps=13740610&shp=30310797&shcp=ff37627b&idc=useast8", "mentions": [], "detailedMentions": [], "text_zh": "❤️😍"}, {"videoWebUrl": "https://www.tiktok.com/@themajorkeyes/video/7605052395382377742", "submittedVideoUrl": "https://www.tiktok.com/@themajorkeyes/video/7605052395382377742", "input": "https://www.tiktok.com/@themajorkeyes/video/7605052395382377742", "cid": "7608585516557517586", "createTime": 1771511875, "createTimeISO": "2026-02-19T14:37:55.000Z", "text": "😭", "diggCount": 0, "likedByAuthor": false, "pinnedByAuthor": false, "repliesToId": null, "replyCommentTotal": 0, "uid": "7588041282280293396", "uniqueId": "user7672265685741", "avatarThumbnail": "https://p16-common-sign.tiktokcdn-us.com/tos-maliva-avt-0068/d0c332b8c14e22bceefe40cbc5a7ff06~tplv-tiktokx-cropcenter:100:100.jpg?dr=9640&refresh_token=809ec7a0&x-expires=1775750400&x-signature=zzV2wyTVQmsEe3TUphn0YVan2kw%3D&t=4d5b0474&ps=13740610&shp=30310797&shcp=ff37627b&idc=useast8", "mentions": [], "detailedMentions": [], "text_zh": "😭"}, {"videoWebUrl": "https://www.tiktok.com/@themajorkeyes/video/7605052395382377742", "submittedVideoUrl": "https://www.tiktok.com/@themajorkeyes/video/7605052395382377742", "input": "https://www.tiktok.com/@themajorkeyes/video/7605052395382377742", "cid": "7608585526203695880", "createTime": 1771511874, "createTimeISO": "2026-02-19T14:37:54.000Z", "text": "🥰", "diggCount": 0, "likedByAuthor": false, "pinnedByAuthor": false, "repliesToId": null, "replyCommentTotal": 0, "uid": "7588041282280293396", "uniqueId": "user7672265685741", "avatarThumbnail": "https://p16-common-sign.tiktokcdn-us.com/tos-maliva-avt-0068/d0c332b8c14e22bceefe40cbc5a7ff06~tplv-tiktokx-cropcenter:100:100.jpg?dr=9640&refresh_token=809ec7a0&x-expires=1775750400&x-signature=zzV2wyTVQmsEe3TUphn0YVan2kw%3D&t=4d5b0474&ps=13740610&shp=30310797&shcp=ff37627b&idc=useast8", "mentions": [], "detailedMentions": [], "text_zh": "🥰"}, {"videoWebUrl": "https://www.tiktok.com/@themajorkeyes/video/7605052395382377742", "submittedVideoUrl": "https://www.tiktok.com/@themajorkeyes/video/7605052395382377742", "input": "https://www.tiktok.com/@themajorkeyes/video/7605052395382377742", "cid": "7608485423358968607", "createTime": 1771488672, "createTimeISO": "2026-02-19T08:11:12.000Z", "text": "🥰🥰🥰", "diggCount": 0, "likedByAuthor": false, "pinnedByAuthor": false, "repliesToId": null, "replyCommentTotal": 0, "uid": "7215465360962159659", "uniqueId": "lovergirlaubs_", "avatarThumbnail": "https://p19-common-sign.tiktokcdn-us.com/tos-useast8-avt-0068-tx2/5a36606423170c53baefefa39d1ac66e~tplv-tiktokx-cropcenter:100:100.jpg?dr=9640&refresh_token=15914ef4&x-expires=1775750400&x-signature=5ZGOHZ0GfvcofJB3fZxHHy5vm6Q%3D&t=4d5b0474&ps=13740610&shp=30310797&shcp=ff37627b&idc=useast8", "mentions": [], "detailedMentions": [], "text_zh": "🥰🥰🥰"}, {"videoWebUrl": "https://www.tiktok.com/@themajorkeyes/video/7605052395382377742", "submittedVideoUrl": "https://www.tiktok.com/@themajorkeyes/video/7605052395382377742", "input": "https://www.tiktok.com/@themajorkeyes/video/7605052395382377742", "cid": "7608352523321672462", "createTime": 1771457640, "createTimeISO": "2026-02-18T23:34:00.000Z", "text": "🥺", "diggCount": 0, "likedByAuthor": false, "pinnedByAuthor": false, "repliesToId": null, "replyCommentTotal": 0, "uid": "7591670767290663949", "uniqueId": "irelynn.dawsey", "avatarThumbnail": "https://p19-common-sign.tiktokcdn-us.com/tos-useast5-avt-0068-tx/6d7734f370e599f27073f3dd025270ae~tplv-tiktokx-cropcenter:100:100.jpg?dr=9640&refresh_token=571fe8e7&x-expires=1775750400&x-signature=7L%2BJ%2B6qxGtPxEwHyOWqpNCx2%2FvY%3D&t=4d5b0474&ps=13740610&shp=30310797&shcp=ff37627b&idc=useast8", "mentions": [], "detailedMentions": [], "text_zh": "🥺"}, {"videoWebUrl": "https://www.tiktok.com/@themajorkeyes/video/7605052395382377742", "submittedVideoUrl": "https://www.tiktok.com/@themajorkeyes/video/7605052395382377742", "input": "https://www.tiktok.com/@themajorkeyes/video/7605052395382377742", "cid": "7608585527046832903", "createTime": 1771511875, "createTimeISO": "2026-02-19T14:37:55.000Z", "text": "✌", "diggCount": 0, "likedByAuthor": false, "pinnedByAuthor": false, "repliesToId": null, "replyCommentTotal": 0, "uid": "7588041282280293396", "uniqueId": "user7672265685741", "avatarThumbnail": "https://p16-common-sign.tiktokcdn-us.com/tos-maliva-avt-0068/d0c332b8c14e22bceefe40cbc5a7ff06~tplv-tiktokx-cropcenter:100:100.jpg?dr=9640&refresh_token=809ec7a0&x-expires=1775750400&x-signature=zzV2wyTVQmsEe3TUphn0YVan2kw%3D&t=4d5b0474&ps=13740610&shp=30310797&shcp=ff37627b&idc=useast8", "mentions": [], "detailedMentions": [], "text_zh": "✌"}, {"videoWebUrl": "https://www.tiktok.com/@themajorkeyes/video/7605052395382377742", "submittedVideoUrl": "https://www.tiktok.com/@themajorkeyes/video/7605052395382377742", "input": "https://www.tiktok.com/@themajorkeyes/video/7605052395382377742", "cid": "7608311977770124062", "createTime": 1771448208, "createTimeISO": "2026-02-18T20:56:48.000Z", "text": "2025", "diggCount": 0, "likedByAuthor": false, "pinnedByAuthor": false, "repliesToId": null, "replyCommentTotal": 0, "uid": "7537477442010629133", "uniqueId": "andrebfsq2b", "avatarThumbnail": "https://p16-common-sign.tiktokcdn-us.com/tos-useast8-avt-0068-tx2/6ec645b0472ede1bd8e10c095cd65552~tplv-tiktokx-cropcenter:100:100.jpg?dr=9640&refresh_token=3e644342&x-expires=1775750400&x-signature=RhnYq40fg0t6%2Fu2R6jH%2Fr682FXw%3D&t=4d5b0474&ps=13740610&shp=30310797&shcp=ff37627b&idc=useast8", "mentions": [], "detailedMentions": [], "text_zh": "2025"}]