[{"videoWebUrl": "https://www.tiktok.com/@digiltony/video/7622100144757935380", "submittedVideoUrl": "https://www.tiktok.com/@digiltony/video/7622100144757935380", "input": "https://www.tiktok.com/@digiltony/video/7622100144757935380", "cid": "7622423474405032724", "createTime": 1774733784, "createTimeISO": "2026-03-28T21:36:24.000Z", "text": "wowww", "diggCount": 0, "likedByAuthor": false, "pinnedByAuthor": false, "repliesToId": null, "replyCommentTotal": 1, "uid": "7620285179500872705", "uniqueId": "hablemossinfiltro2", "avatarThumbnail": "https://p16-common-sign.tiktokcdn-us.com/tos-alisg-avt-0068/20ab90745129f1193fb5d1016d059c60~tplv-tiktokx-cropcenter:100:100.jpg?dr=9640&refresh_token=e3ed6772&x-expires=1775754000&x-signature=dzyFZMW6d%2FB%2FkL1fVXJlX0iHM5g%3D&t=4d5b0474&ps=13740610&shp=30310797&shcp=ff37627b&idc=useast5", "mentions": [], "detailedMentions": [], "text_zh": "哇哦哇哦"}]